[
  {
    "original_url": "http://127.0.0.1:3000/?v=1720391327463",
    "short_url": 762
  },
  {
    "original_url": "http://127.0.0.1:3000/?v=1720391327504",
    "short_url": 895
  },
  {
    "original_url": "http://127.0.0.1:3000/?v=1720391332997",
    "short_url": 579
  },
  {
    "original_url": "http://127.0.0.1:3000/?v=1720391333007",
    "short_url": 2007
  },
  {
    "original_url": "http://127.0.0.1:3000/?v=1720391419584",
    "short_url": 578
  },
  {
    "original_url": "http://127.0.0.1:3000/?v=1720391419592",
    "short_url": 67
  }
]